{"cameraMode":{"drawMode":0,"name":"Shaded","section":"Shading Mode"},"sceneLighting":false,"audioPlay":false,"sceneViewState":{"showFog":false,"showMaterialUpdate":true,"showSkybox":false,"showFlares":true,"showImageEffects":true,"showParticleSystems":true,"showVisualEffectGraphs":true,"m_FxEnabled":false},"in2DMode":false,"pivot":{"x":0.0,"y":1.8400001525878907,"z":0.8399999141693115},"rotation":{"x":0.13074958324432374,"y":0.7013086676597595,"z":-0.13328273594379426,"w":0.6879732608795166},"size":4.01566219329834,"orthographic":false}